python_modhex/__init__.py
python_modhex/_version.py
python_modhex/python_modhex.py
python_modhex-0.0.2.data/scripts/python_modhex
python_modhex-0.0.2.dist-info/METADATA
python_modhex-0.0.2.dist-info/WHEEL
python_modhex-0.0.2.dist-info/top_level.txt
python_modhex-0.0.2.dist-info/RECORD
