Metadata-Version: 2.1
Name: python-modhex
Version: 0.0.2
Summary: Very simple modhex library when working with yubikey OTPs.
Home-page: https://github.com/normoes/python_modhex
Author: Norman Moeschter-Schenck
Author-email: <norman.moeschter@gmail.com>
Maintainer: Norman Moeschter-Schenck
Maintainer-email: <norman.moeschter@gmail.com>
License: UNKNOWN
Download-URL: https://github.com/normoes/python_modhex/archive/v0.0.2.tar.gz
Platform: UNKNOWN
Classifier: License :: OSI Approved :: MIT License
Classifier: Operating System :: OS Independent
Classifier: Programming Language :: Python :: 3.7
